finance_calculator/__init__.py
finance_calculator/__main__.py
finance_calculator/calculator.py
finance_calculator_NovEf-0.2.dist-info/METADATA
finance_calculator_NovEf-0.2.dist-info/WHEEL
finance_calculator_NovEf-0.2.dist-info/entry_points.txt
finance_calculator_NovEf-0.2.dist-info/top_level.txt
finance_calculator_NovEf-0.2.dist-info/RECORD
