Metadata-Version: 2.1
Name: finance-calculator-NovEf
Version: 0.2
Summary: A package for calculating net profit and ROI
Home-page: UNKNOWN
Author: Novoselov Efim
Author-email: kuku@mail.com
License: UNKNOWN
Platform: UNKNOWN
